loguru3/__init__.py
loguru3/__init__.pyi
loguru3/_asyncio_loop.py
loguru3/_better_exceptions.py
loguru3/_colorama.py
loguru3/_colorizer.py
loguru3/_contextvars.py
loguru3/_ctime_functions.py
loguru3/_datetime.py
loguru3/_defaults.py
loguru3/_error_interceptor.py
loguru3/_file_sink.py
loguru3/_filters.py
loguru3/_get_frame.py
loguru3/_handler.py
loguru3/_locks_machinery.py
loguru3/_logger.py
loguru3/_recattrs.py
loguru3/_simple_sinks.py
loguru3/_string_parsers.py
loguru3/py.typed
loguru3-0.1.0.dist-info/METADATA
loguru3-0.1.0.dist-info/WHEEL
loguru3-0.1.0.dist-info/RECORD
